MANIFEST.in
README.md
setup.py
categories/__init__.py
categories/admin.py
categories/apps.py
categories/fields.py
categories/models.py
categories/translation.py
categories/locale/ru/LC_MESSAGES/django.mo
categories/locale/ru/LC_MESSAGES/django.po
categories/locale/uk/LC_MESSAGES/django.mo
categories/locale/uk/LC_MESSAGES/django.po
categories/management/__init__.py
categories/management/commands/__init__.py
categories/management/commands/import_prom_categories.py
categories/migrations/0001_initial.py
categories/migrations/0002_title.py
categories/migrations/0003_description.py
categories/migrations/0004_code.py
categories/migrations/0005_logo.py
categories/migrations/0006_icon.py
categories/migrations/0007_translation_fields.py
categories/migrations/0008_mptt.py
categories/migrations/0009_order.py
categories/migrations/__init__.py
categories/templatetags/__init__.py
categories/templatetags/categories.py
django_mp_categories.egg-info/PKG-INFO
django_mp_categories.egg-info/SOURCES.txt
django_mp_categories.egg-info/dependency_links.txt
django_mp_categories.egg-info/top_level.txt