Metadata-Version: 2.1
Name: django-mp-categories
Version: 3.0.4
Summary: Django categories app
Home-page: https://github.com/pmaigutyak/mp-categories
Author: Paul Maigutyak
Author-email: pmaigutyak@gmail.com
License: MIT
Download-URL: https://github.com/pmaigutyak/mp-categories/archive/3.0.4.tar.gz
Platform: UNKNOWN
